{
    "animals": [
        {
          "id": -7,
          "name": "Speedy Gonzales",
          "genre": "Mamifère",
          "birthday": 125963258,
          "img": "https://i.guim.co.uk/img/media/3b516cb39a65905afae6b8f895c145d603cc33ee/0_178_1600_960/master/1600.jpg?width=1200&height=900&quality=85&auto=format&fit=crop&s=f8c4e5cceba243d6e31b60589c3ce1bd",
          "veterinaire": "John Doe",
          "commentaire": "La souris la plou rapide du monde..."
        },
        {
          "id": -6,
          "name": "Mickey",
          "genre": "Mamifère",
          "birthday": 125963258,
          "veterinaire": "",
          "commentaire": "",
          "img": "https://i.pinimg.com/originals/65/d6/cf/65d6cfcb2bb5193d6d160157b34b2bd0.png"
        },
        {
          "id": -5,
          "name": "Robert",
          "genre": "A plumes",
          "birthday": 125963258,
          "veterinaire": "",
          "commentaire": "",
          "img": "https://www.villagesdecorse.fr/photos/articles/faune/oiseaux/milan-royal/milan-royal.webp"
        },
        {
          "id": -4,
          "name": "Bulle",
          "genre": "Poisson",
          "birthday": 125963258,
          "veterinaire": "",
          "commentaire": "",
          "img": "https://www.google.com/url?sa=i&url=https%3A%2F%2Fwww.floraquatic.com%2Fpoissons-d-eau-froide%2F5127-carassius-auratus-6-7cm-3701376512605.html&psig=AOvVaw3AdvgjXZgvuiNkNB6neFxv&ust=1601029126934000&source=images&cd=vfe&ved=0CAIQjRxqFwoTCOCp97TIgewCFQAAAAAdAAAAABAE"
        },
        {
          "id": -3,
          "name": "Choupi",
          "genre": "Reptile",
          "birthday": 125963258,
          "veterinaire": "",
          "commentaire": "",
          "img": "https://pbs.twimg.com/profile_images/1188552758544216065/zQvAW7dD_400x400.jpg"
        },
        {
          "id": -2,
          "name": "Bob",
          "genre": "Amphibien",
          "birthday": 125963258,
          "veterinaire": "",
          "commentaire": "",
          "img": "https://home.adelphi.edu/~sc16910/AF581~Frog-Posters.jpg"
        },
        {
          "id": -1,
          "name": "Kermit",
          "genre": "Amphibien",
          "birthday": 125963258,
          "veterinaire": "",
          "commentaire": "",
          "img": "https://i.pinimg.com/originals/cf/a7/78/cfa778906e740ed2bc364d4e8bac66e0.jpg"
        },
        {
            "id": 0,
            "name": "psychecat",
            "genre": "défoncé",
            "birthday": 123456789,
            "veterinaire": "",
            "commentaire": "",
            "img": "https://i.pinimg.com/originals/51/2a/6e/512a6e1cbacff60df8c23bec15492ebb.gif"
          },
          {
            "id": 1,
            "name": "felix le chat",
            "genre": "femelle",
            "birthday": 123456789,
            "veterinaire": "",
            "commentaire": "",
            "img": "https://media.standaardboekhandel.be/product-image?code=9782824610542&size=small"
          },
          {
            "id": 2,
            "name": "simon le chat",
            "genre": "male",
            "birthday": 9876543219,
            "veterinaire": "",
            "commentaire": "",
            "img": "https://dieux.me/storage/cache/images/000/007/PNpY1-bEe-wlAYyhtE-VJOoqETw,medium.2x.1425914604.jpg"
          },
          {
            "id": 3,
            "name": "truc",
            "genre": "male",
            "birthday": 123456666,
            "veterinaire": "",
            "commentaire": "",
            "img": "https://i.pinimg.com/originals/4c/4e/a9/4c4ea980e73028057eefe4200e903bec.gif"
          }
    ]
}